docs/examples.md
docs/index.md
docs/install.md
qlient/http/__init__.py
qlient/http/backends.py
qlient/http/clients.py
qlient/http/consts.py
qlient/http/exceptions.py
qlient/http/models.py
qlient/http/settings.py
qlient-1.0.0.dist-info/LICENSE
qlient-1.0.0.dist-info/WHEEL
qlient-1.0.0.dist-info/METADATA
qlient-1.0.0.dist-info/RECORD
