Metadata-Version: 2.1
Name: qlient
Version: 1.0.0
Summary: A fast and modern graphql client designed with simplicity in mind.
Home-page: https://qlient-org.github.io/python-qlient/
License: MIT
Keywords: graphql,client,api,query,mutation
Author: Daniel Seifert
Author-email: info@danielseifert.ch
Maintainer: Daniel Seifert
Maintainer-email: info@danielseifert.ch
Requires-Python: >=3.7,<4.0
Classifier: Development Status :: 5 - Production/Stable
Classifier: Intended Audience :: Developers
Classifier: License :: OSI Approved :: MIT License
Classifier: Natural Language :: English
Classifier: Programming Language :: Python
Classifier: Programming Language :: Python :: 3
Classifier: Programming Language :: Python :: 3.10
Classifier: Programming Language :: Python :: 3.7
Classifier: Programming Language :: Python :: 3.8
Classifier: Programming Language :: Python :: 3.9
Classifier: Programming Language :: Python :: Implementation :: CPython
Classifier: Programming Language :: Python :: Implementation :: PyPy
Requires-Dist: qlient-core (>=1.0.1,<2.0.0)
Requires-Dist: requests (>=2.27.1,<3.0.0)
Requires-Dist: websocket-client (>=1.3.3,<2.0.0)
Project-URL: Documentation, https://qlient-org.github.io/python-qlient/
Project-URL: Repository, https://github.com/qlient-org/python-qlient
